microdbx/__init__.py
microdbx/flash.py
microdbx/ram.py
microdbx-0.1.1.dist-info/licenses/LICENSE
microdbx-0.1.1.dist-info/METADATA
microdbx-0.1.1.dist-info/WHEEL
microdbx-0.1.1.dist-info/top_level.txt
microdbx-0.1.1.dist-info/RECORD
