Metadata-Version: 2.4
Name: microdbx
Version: 0.1.1
Summary: Lightweight key-value database for microcontrollers with Flash and RAM storage backends.
Author: netcorelink
License: MIT
Project-URL: Homepage, https://github.com/netcorelink/microdbx
Project-URL: Repository, https://github.com/netcorelink/microdbx
Project-URL: Documentation, https://github.com/netcorelink/microdbx#readme
Keywords: db,flash,ram,microcontroller,micropython,iot
Classifier: Programming Language :: Python :: 3
Classifier: Programming Language :: Python :: 3.8
Classifier: License :: OSI Approved :: MIT License
Classifier: Operating System :: OS Independent
Classifier: Intended Audience :: Developers
Classifier: Typing :: Typed
Requires-Python: >=3.8
License-File: LICENSE
Dynamic: license-file
